<?xml version="1.0"?>
<dc-workflow workflow_id="organs_one_state_workflow" title="Single State Workflow" description="- Essentially a workflow with no transitions, but has a Published state, so portlets and applications that expect that state will continue to work." state_variable="review_state" initial_state="published" manager_bypass="True">
 <permission>Access contents information</permission>
 <permission>Add Workflow Policy</permission>
 <permission>Add portal content</permission>
 <permission>Change portal events</permission>
 <permission>Copy or Move</permission>
 <permission>Delete objects</permission>
 <permission>List folder contents</permission>
 <permission>Manage portal</permission>
 <permission>Modify portal content</permission>
 <permission>Public, everyone can access</permission>
 <permission>Reply to item</permission>
 <permission>Review portal content</permission>
 <permission>Sharing page: Delegate Contributor role</permission>
 <permission>Sharing page: Delegate Editor role</permission>
 <permission>Sharing page: Delegate Reader role</permission>
 <permission>Sharing page: Delegate Reviewer role</permission>
 <permission>Sharing page: Delegate roles</permission>
 <permission>View</permission>
 <permission>View History</permission>
 <permission>plone.app.multilingual: Manage Translations</permission>
 <state state_id="published" title="Published">
  <description>Visible to everyone, editable by the owner.</description>
  <permission-map name="Access contents information" acquired="True">
   <permission-role>Anonymous</permission-role>
   <permission-role>Authenticated</permission-role>
   <permission-role>Editor</permission-role>
   <permission-role>Manager</permission-role>
   <permission-role>OG1-Secretari</permission-role>
   <permission-role>OG2-Editor</permission-role>
   <permission-role>Site Administrator</permission-role>
   <permission-role>WebMaster</permission-role>
  </permission-map>
  <permission-map name="Add Workflow Policy" acquired="True">
   <permission-role>Editor</permission-role>
   <permission-role>Manager</permission-role>
   <permission-role>OG1-Secretari</permission-role>
   <permission-role>OG2-Editor</permission-role>
  </permission-map>
  <permission-map name="Add portal content" acquired="False">
   <permission-role>Manager</permission-role>
   <permission-role>OG1-Secretari</permission-role>
   <permission-role>OG2-Editor</permission-role>
   <permission-role>Site Administrator</permission-role>
   <permission-role>WebMaster</permission-role>
  </permission-map>
  <permission-map name="Change portal events" acquired="True">
   <permission-role>Editor</permission-role>
   <permission-role>Manager</permission-role>
   <permission-role>OG1-Secretari</permission-role>
   <permission-role>OG2-Editor</permission-role>
   <permission-role>Owner</permission-role>
   <permission-role>Site Administrator</permission-role>
   <permission-role>WebMaster</permission-role>
  </permission-map>
  <permission-map name="Copy or Move" acquired="False">
   <permission-role>Manager</permission-role>
   <permission-role>OG1-Secretari</permission-role>
  </permission-map>
  <permission-map name="Delete objects" acquired="False">
   <permission-role>Editor</permission-role>
   <permission-role>Manager</permission-role>
   <permission-role>OG1-Secretari</permission-role>
   <permission-role>Owner</permission-role>
   <permission-role>Site Administrator</permission-role>
   <permission-role>WebMaster</permission-role>
  </permission-map>
  <permission-map name="List folder contents" acquired="True">
   <permission-role>Editor</permission-role>
   <permission-role>Manager</permission-role>
   <permission-role>OG1-Secretari</permission-role>
   <permission-role>Site Administrator</permission-role>
   <permission-role>WebMaster</permission-role>
  </permission-map>
  <permission-map name="Manage portal" acquired="True">
   <permission-role>Manager</permission-role>
   <permission-role>OG1-Secretari</permission-role>
   <permission-role>OG2-Editor</permission-role>
  </permission-map>
  <permission-map name="Modify portal content" acquired="True">
   <permission-role>Editor</permission-role>
   <permission-role>Manager</permission-role>
   <permission-role>OG1-Secretari</permission-role>
   <permission-role>OG2-Editor</permission-role>
   <permission-role>Owner</permission-role>
   <permission-role>Site Administrator</permission-role>
   <permission-role>WebMaster</permission-role>
  </permission-map>
  <permission-map name="Public, everyone can access" acquired="True">
   <permission-role>Editor</permission-role>
   <permission-role>Manager</permission-role>
   <permission-role>OG1-Secretari</permission-role>
   <permission-role>OG2-Editor</permission-role>
  </permission-map>
  <permission-map name="Reply to item" acquired="True">
   <permission-role>Editor</permission-role>
   <permission-role>Manager</permission-role>
   <permission-role>OG1-Secretari</permission-role>
   <permission-role>OG2-Editor</permission-role>
   <permission-role>Site Administrator</permission-role>
   <permission-role>WebMaster</permission-role>
  </permission-map>
  <permission-map name="Review portal content" acquired="True">
   <permission-role>Editor</permission-role>
   <permission-role>Manager</permission-role>
   <permission-role>OG1-Secretari</permission-role>
   <permission-role>OG2-Editor</permission-role>
   <permission-role>OG3-Membre</permission-role>
  </permission-map>
  <permission-map name="Sharing page: Delegate Contributor role" acquired="False">
   <permission-role>Manager</permission-role>
   <permission-role>OG1-Secretari</permission-role>
   <permission-role>WebMaster</permission-role>
  </permission-map>
  <permission-map name="Sharing page: Delegate Editor role" acquired="False">
   <permission-role>Manager</permission-role>
   <permission-role>OG1-Secretari</permission-role>
   <permission-role>WebMaster</permission-role>
  </permission-map>
  <permission-map name="Sharing page: Delegate Reader role" acquired="False">
   <permission-role>Manager</permission-role>
   <permission-role>OG1-Secretari</permission-role>
   <permission-role>WebMaster</permission-role>
  </permission-map>
  <permission-map name="Sharing page: Delegate Reviewer role" acquired="False">
   <permission-role>Manager</permission-role>
   <permission-role>OG1-Secretari</permission-role>
   <permission-role>WebMaster</permission-role>
  </permission-map>
  <permission-map name="Sharing page: Delegate roles" acquired="False">
   <permission-role>Manager</permission-role>
   <permission-role>OG1-Secretari</permission-role>
   <permission-role>WebMaster</permission-role>
  </permission-map>
  <permission-map name="View" acquired="True">
   <permission-role>Anonymous</permission-role>
   <permission-role>Authenticated</permission-role>
   <permission-role>Editor</permission-role>
   <permission-role>Manager</permission-role>
   <permission-role>OG1-Secretari</permission-role>
   <permission-role>OG2-Editor</permission-role>
   <permission-role>OG3-Membre</permission-role>
   <permission-role>OG4-Afectat</permission-role>
   <permission-role>Site Administrator</permission-role>
   <permission-role>WebMaster</permission-role>
  </permission-map>
  <permission-map name="View History" acquired="True">
   <permission-role>Editor</permission-role>
   <permission-role>Manager</permission-role>
   <permission-role>OG1-Secretari</permission-role>
   <permission-role>OG2-Editor</permission-role>
  </permission-map>
  <permission-map name="plone.app.multilingual: Manage Translations" acquired="True">
   <permission-role>Editor</permission-role>
   <permission-role>Manager</permission-role>
   <permission-role>OG1-Secretari</permission-role>
   <permission-role>OG2-Editor</permission-role>
  </permission-map>
 </state>
 <variable variable_id="action" for_catalog="False" for_status="True" update_always="True">
  <description>Previous transition</description>
  <default>
   
   <expression>transition/getId|nothing</expression>
  </default>
  <guard>
  </guard>
 </variable>
 <variable variable_id="actor" for_catalog="False" for_status="True" update_always="True">
  <description>The ID of the user who performed the previous transition</description>
  <default>
   
   <expression>user/getId</expression>
  </default>
  <guard>
  </guard>
 </variable>
 <variable variable_id="comments" for_catalog="False" for_status="True" update_always="True">
  <description>Comment about the last transition</description>
  <default>
   
   <expression>python:state_change.kwargs.get('comment', '')</expression>
  </default>
  <guard>
  </guard>
 </variable>
 <variable variable_id="review_history" for_catalog="False" for_status="False" update_always="False">
  <description>Provides access to workflow history</description>
  <default>
   
   <expression>state_change/getHistory</expression>
  </default>
  <guard>
   <guard-permission>Request review</guard-permission>
   <guard-permission>Review portal content</guard-permission>
  </guard>
 </variable>
 <variable variable_id="time" for_catalog="False" for_status="True" update_always="True">
  <description>When the previous transition was performed</description>
  <default>
   
   <expression>state_change/getDateTime</expression>
  </default>
  <guard>
  </guard>
 </variable>
</dc-workflow>
